hackgap/cptasks_kmers.py
hackgap/dnaencode.py
hackgap/fastcash_filter.py
hackgap/fastcash_info.py
hackgap/fastcash_main.py
hackgap/filter_bi_b3c.py
hackgap/hash_s3c_fbcbvb.py
hackgap/hashfunctions.py
hackgap/mask.py
hackgap/mathutils.py
hackgap/parameters.py
hackgap/srhash.py
hackgap/subtable_hashfunctions.py
hackgap/hackgap/hackgap_count.py
hackgap/hackgap/hackgap_main.py
hackgap/hackgap/hackgap_pycount.py
hackgap/hackgap/hackgap_weak.py
hackgap/io/binaryio.py
hackgap/io/fastaio.py
hackgap/io/fastqio.py
hackgap/io/filterio.py
hackgap/io/generaldsio.py
hackgap/io/generalio.py
hackgap/io/hashio.py
hackgap/io/seqio.py
hackgap/io/textio.py
hackgap/io/xorio.py
hackgap/lowlevel/aligned_arrays.py
hackgap/lowlevel/bitarray.py
hackgap/lowlevel/conpro.py
hackgap/lowlevel/debug.py
hackgap/lowlevel/intbitarray.py
hackgap/lowlevel/libc.py
hackgap/lowlevel/llvm.py
hackgap/lowlevel/lowlevelfunctions.txt
hackgap/lowlevel/numbautils.py
hackgap/lowlevel/packedarray.py
hackgap/values/count.py
hackgap/values/countweak.py
hackgap-1.0.1.dist-info/LICENSE
hackgap-1.0.1.dist-info/METADATA
hackgap-1.0.1.dist-info/WHEEL
hackgap-1.0.1.dist-info/entry_points.txt
hackgap-1.0.1.dist-info/top_level.txt
hackgap-1.0.1.dist-info/RECORD
