Metadata-Version: 2.2
Name: hackgap
Version: 1.0.1
Summary: hash-based counting of k-mers with gaps using a fast jit-compiled k-mer counter
Author-email: Jens Zentgraf <zentgraf@cs.uni-saarland.de>, Sven Rahmann <rahmann@cs.uni-saarland.de>
License: MIT License
Project-URL: Homepage, https://gitlab.com/rahmannlab/hackgap
Project-URL: Bug Tracker, https://gitlab.com/rahmannlab/hackgap/issues
Classifier: Programming Language :: Python :: 3
Classifier: License :: OSI Approved :: MIT License
Classifier: Operating System :: OS Independent
Classifier: Development Status :: 5 - Production/Stable
Classifier: Environment :: Console
Classifier: Intended Audience :: Science/Research
Classifier: Natural Language :: English
Classifier: Topic :: Scientific/Engineering :: Bio-Informatics
Requires-Python: >=3.12
License-File: LICENSE
Requires-Dist: numpy>=2
Requires-Dist: numba>=0.60
Requires-Dist: pytest
Requires-Dist: pip
